gfModParser/__init__.py
gfModParser/io.py
gfModParser/utils.py
gfModParser/modules/arrays.py
gfModParser/modules/attributes.py
gfModParser/modules/components.py
gfModParser/modules/expressions.py
gfModParser/modules/generics.py
gfModParser/modules/mod.py
gfModParser/modules/namelists.py
gfModParser/modules/namespaces.py
gfModParser/modules/operators.py
gfModParser/modules/procedures.py
gfModParser/modules/properties.py
gfModParser/modules/simds.py
gfModParser/modules/summary.py
gfModParser/modules/symbols.py
gfModParser/modules/utils.py
gfmodparser-1.1.1.dist-info/licenses/COPYING.txt
gfmodparser-1.1.1.dist-info/METADATA
gfmodparser-1.1.1.dist-info/WHEEL
gfmodparser-1.1.1.dist-info/top_level.txt
gfmodparser-1.1.1.dist-info/RECORD
