Metadata-Version: 2.4
Name: gfModParser
Version: 1.1.1
Summary: Parser for gfortran's Fortran module file format.
Author-email: Robert Farmer <robert.j.farmer37@gmail.com>
License: GPLv2+
Classifier: Programming Language :: Python :: 3
Classifier: Programming Language :: Python :: 3 :: Only
Classifier: Programming Language :: Python :: 3.10
Classifier: Programming Language :: Python :: 3.11
Classifier: Programming Language :: Python :: 3.12
Classifier: Programming Language :: Python :: 3.13
Classifier: Topic :: Software Development :: Code Generators
Requires-Python: >=3.10
License-File: COPYING.txt
Requires-Dist: numpy<2.3
Provides-Extra: test
Requires-Dist: pytest; extra == "test"
Requires-Dist: pytest-xdist; extra == "test"
Provides-Extra: coverage
Requires-Dist: pytest; extra == "coverage"
Requires-Dist: pytest-xdist; extra == "coverage"
Requires-Dist: pytest-cov; extra == "coverage"
Provides-Extra: quad
Requires-Dist: pyquadp; extra == "quad"
Provides-Extra: dev
Requires-Dist: pre-commit; extra == "dev"
Requires-Dist: black; extra == "dev"
Requires-Dist: pytest; extra == "dev"
Requires-Dist: pytest-xdist; extra == "dev"
Provides-Extra: perfomance
Requires-Dist: pytest; extra == "perfomance"
Requires-Dist: pytest-codspeed; extra == "perfomance"
Requires-Dist: pytest-xdist; extra == "perfomance"
Provides-Extra: types
Requires-Dist: mypy; extra == "types"
Requires-Dist: types-setuptools; extra == "types"
Dynamic: license-file
